fastapi_error_map/__init__.py
fastapi_error_map/error_handling.py
fastapi_error_map/openapi.py
fastapi_error_map/py.typed
fastapi_error_map/routing.py
fastapi_error_map/rules.py
fastapi_error_map/translator_policy.py
fastapi_error_map/translators.py
fastapi_error_map-0.9.6.dist-info/METADATA
fastapi_error_map-0.9.6.dist-info/WHEEL
fastapi_error_map-0.9.6.dist-info/licenses/LICENSE
fastapi_error_map-0.9.6.dist-info/RECORD
