Metadata-Version: 2.4
Name: fastapi-error-map
Version: 0.9.6
Summary: Elegant per-endpoint error handling for FastAPI that keeps OpenAPI in sync
Project-URL: Homepage, https://github.com/ivan-borovets/fastapi-error-map
Project-URL: Repository, https://github.com/ivan-borovets/fastapi-error-map
Author-email: Ivan Borovets <ivan.r.borovets@gmail.com>
License: Apache-2.0
License-File: LICENSE
Classifier: Framework :: FastAPI
Classifier: Intended Audience :: Developers
Classifier: License :: OSI Approved :: Apache Software License
Classifier: Operating System :: OS Independent
Classifier: Programming Language :: Python :: 3
Classifier: Programming Language :: Python :: 3.9
Classifier: Programming Language :: Python :: 3.10
Classifier: Programming Language :: Python :: 3.11
Classifier: Programming Language :: Python :: 3.12
Classifier: Programming Language :: Python :: 3.13
Classifier: Topic :: Software Development :: Libraries
Classifier: Typing :: Typed
Requires-Python: >=3.9
Requires-Dist: fastapi>=0.100.0
Requires-Dist: orjson>=3.8.4
Provides-Extra: dev
Requires-Dist: mypy==1.8.0; extra == 'dev'
Requires-Dist: pre-commit==4.2.0; extra == 'dev'
Requires-Dist: ruff==0.11.2; extra == 'dev'
Provides-Extra: examples
Requires-Dist: uvicorn==0.35.0; extra == 'examples'
Provides-Extra: publish
Requires-Dist: hatch==1.14.1; extra == 'publish'
Provides-Extra: test
Requires-Dist: coverage==7.10.1; extra == 'test'
Requires-Dist: httpx==0.28.1; extra == 'test'
Requires-Dist: nox==2025.5.1; extra == 'test'
Requires-Dist: pytest-asyncio==1.1.0; extra == 'test'
Requires-Dist: pytest-cov==6.2.1; extra == 'test'
Requires-Dist: pytest==8.4.1; extra == 'test'
